[
  {"id": "w4_1", "word": "running", "definition": "The action or movement of a runner.", "sentence_context": "He is running in the marathon.", "difficulty": 1},
  {"id": "w4_2", "word": "happily", "definition": "In a happy manner.", "sentence_context": "The children played happily in the park.", "difficulty": 1},
  {"id": "w4_3", "word": "baked", "definition": "Cooked by dry heat in an oven.", "sentence_context": "She baked a delicious cake.", "difficulty": 1},
  {"id": "w4_4", "word": "crying", "definition": "Shedding tears.", "sentence_context": "The baby was crying for milk.", "difficulty": 1},
  {"id": "w4_5", "word": "stopped", "definition": "Ceased to move or proceed.", "sentence_context": "The car stopped at the red light.", "difficulty": 1},
  {"id": "w4_6", "word": "planning", "definition": "The process of making plans for something.", "sentence_context": "They are planning a surprise party.", "difficulty": 1},
  {"id": "w4_7", "word": "heavier", "definition": "Of great weight.", "sentence_context": "This box is heavier than the other one.", "difficulty": 1},
  {"id": "w4_8", "word": "biggest", "definition": "Of considerable size or extent.", "sentence_context": "That is the biggest elephant I have ever seen.", "difficulty": 1},
  {"id": "w4_9", "word": "carried", "definition": "Supported and moved from one place to another.", "sentence_context": "He carried the groceries into the house.", "difficulty": 1},
  {"id": "w4_10", "word": "shining", "definition": "Giving out or reflecting light.", "sentence_context": "The sun is shining brightly today.", "difficulty": 1},
  {"id": "w4_11", "word": "beautifully", "definition": "In a beautiful manner.", "sentence_context": "She sings beautifully.", "difficulty": 2},
  {"id": "w4_12", "word": "dropped", "definition": "Let fall vertically.", "sentence_context": "He dropped his keys on the floor.", "difficulty": 2},
  {"id": "w4_13", "word": "earliest", "definition": "Happening or done before the usual or expected time.", "sentence_context": "What is the earliest you can arrive?", "difficulty": 2},
  {"id": "w4_14", "word": "grabbed", "definition": "Grasped or seized suddenly and roughly.", "sentence_context": "He grabbed his coat and left.", "difficulty": 2},
  {"id": "w4_15", "word": "hurrying", "definition": "Moving or proceeding with great speed.", "sentence_context": "Why are you hurrying so much?", "difficulty": 2},
  {"id": "w4_16", "word": "laziest", "definition": "Unwilling to work or use energy.", "sentence_context": "He is the laziest cat in the world.", "difficulty": 2},
  {"id": "w4_17", "word": "prettier", "definition": "Attractive in a delicate way.", "sentence_context": "This flower is prettier than that one.", "difficulty": 2},
  {"id": "w4_18", "word": "swimming", "definition": "The sport or activity of propelling oneself through water.", "sentence_context": "I love swimming in the ocean.", "difficulty": 2},
  {"id": "w4_19", "word": "tripped", "definition": "Catch one's foot on something and stumble or fall.", "sentence_context": "He tripped over the rug.", "difficulty": 2},
  {"id": "w4_20", "word": "worried", "definition": "Anxious or troubled about actual or potential problems.", "sentence_context": "She was worried about her exam.", "difficulty": 2},
  {"id": "w4_21", "word": "baking", "definition": "The action of cooking by dry heat.", "sentence_context": "The smell of baking filled the house.", "difficulty": 1},
  {"id": "w4_22", "word": "danced", "definition": "Moved rhythmically to music.", "sentence_context": "They danced all night.", "difficulty": 1},
  {"id": "w4_23", "word": "dried", "definition": "Became free of moisture.", "sentence_context": "He dried his hands on the towel.", "difficulty": 1},
  {"id": "w4_24", "word": "faster", "definition": "At a high speed.", "sentence_context": "Can you run any faster?", "difficulty": 1},
  {"id": "w4_25", "word": "filling", "definition": "Making something full.", "sentence_context": "She is filling the bottle with water.", "difficulty": 1},
  {"id": "w4_26", "word": "gently", "definition": "In a mild or kind manner.", "sentence_context": "Hold the baby gently.", "difficulty": 1},
  {"id": "w4_27", "word": "hopped", "definition": "Jumped on one foot.", "sentence_context": "The bird hopped along the branch.", "difficulty": 1},
  {"id": "w4_28", "word": "jumping", "definition": "Pushing oneself off the ground.", "sentence_context": "The children were jumping on the bed.", "difficulty": 1},
  {"id": "w4_29", "word": "liked", "definition": "Found something pleasant.", "sentence_context": "I liked the movie very much.", "difficulty": 1},
  {"id": "w4_30", "word": "making", "definition": "Creating or forming something.", "sentence_context": "We are making a card for Mom.", "difficulty": 1},
  {"id": "w4_31", "word": "played", "definition": "Engaged in activity for enjoyment.", "sentence_context": "They played soccer in the park.", "difficulty": 1},
  {"id": "w4_32", "word": "riding", "definition": "Sitting on and controlling an animal or vehicle.", "sentence_context": "She is riding her bike.", "difficulty": 1},
  {"id": "w4_33", "word": "safely", "definition": "In a way that is not likely to cause danger.", "sentence_context": "They arrived safely at home.", "difficulty": 2},
  {"id": "w4_34", "word": "sitting", "definition": "Being in a position with the weight supported by the buttocks.", "sentence_context": "He was sitting in the chair.", "difficulty": 1},
  {"id": "w4_35", "word": "skating", "definition": "Moving on skates.", "sentence_context": "We went skating on the frozen pond.", "difficulty": 1},
  {"id": "w4_36", "word": "smiled", "definition": "Formed one's features into a pleased or kind expression.", "sentence_context": "The teacher smiled at the class.", "difficulty": 1},
  {"id": "w4_37", "word": "talking", "definition": "Speaking in order to give information or express ideas.", "sentence_context": "They were talking about their summer plans.", "difficulty": 1},
  {"id": "w4_38", "word": "walked", "definition": "Moved at a regular pace by lifting and setting down each foot in turn.", "sentence_context": "He walked to the store.", "difficulty": 1},
  {"id": "w4_39", "word": "winner", "definition": "A person or thing that wins something.", "sentence_context": "The winner received a trophy.", "difficulty": 2},
  {"id": "w4_40", "word": "writing", "definition": "The activity of marking with letters.", "sentence_context": "She is writing a story.", "difficulty": 1}
]
